{
  "id": "battlecards:illager_pack/johnny/blood_for_blood",
  "quickKeywords": ["Attack","Melee","Mana Generator"],
  "quickEffects": [
    {
      "effect": "melee",
      "isSweep": "false",
      "onHit": [
        {
          "effect": "damage",
          "amount": 5,
          "damageType": "minecraft:player_attack"
        },
        {
          "effect": "gain_mana",
          "amount": 2
        }
      ]
    }
  ],
  "cost": 5,
  "chargeKeywords": ["Attack","Melee","Healing"],
  "chargeEffects": [
    {
      "effect": "melee",
      "onHit": [
        {
          "effect": "damage",
          "amount": {
            "effect": "addition_scalar",
            "a": 5,
            "b": {
              "effect": "recent_damage_scalar",
              "maxTicks": 10
            }
          },
          "damageType": "minecraft:player_attack",
          "afterDamage": [
            {
              "effect": "lifesteal",
              "amount": 1.0
            }
          ]
        }
      ]
    }
  ]
}